Workbook

Sheet Resumen
A1: Resumen por público
A2: Se calcula solo. No escribas nada en esta hoja.
A4: Público | B4: Leads | C4: Ventas | D4: Gasto US$ | E4: Ingreso US$ | F4: Costo x lead | G4: Costo x venta | H4: Tasa de cierre | I4: Retorno
A5: A · Admins | B5: =COUNTIFS(Leads!$F$7:$F$305,$A5) -> 0 | C5: =COUNTIFS(Leads!$F$7:$F$305,$A5,Leads!$H$7:$H$305,"Sí") -> 0 | D5: =SUM('Gasto diario'!$B$5:$B$95) -> 0 | E5: =SUMIFS(Leads!$I$7:$I$305,Leads!$F$7:$F$305,$A5,Leads!$H$7:$H$305,"Sí") -> 0 | F5: =IF($B5=0,"-",$D5/$B5) -> - | G5: =IF($C5=0,"-",$D5/$C5) -> - | H5: =IF($B5=0,"-",$C5/$B5) -> - | I5: =IF($D5=0,"-",$E5/$D5) -> -
A6: B · Gastronomía | B6: =COUNTIFS(Leads!$F$7:$F$305,$A6) -> 0 | C6: =COUNTIFS(Leads!$F$7:$F$305,$A6,Leads!$H$7:$H$305,"Sí") -> 0 | D6: =SUM('Gasto diario'!$C$5:$C$95) -> 0 | E6: =SUMIFS(Leads!$I$7:$I$305,Leads!$F$7:$F$305,$A6,Leads!$H$7:$H$305,"Sí") -> 0 | F6: =IF($B6=0,"-",$D6/$B6) -> - | G6: =IF($C6=0,"-",$D6/$C6) -> - | H6: =IF($B6=0,"-",$C6/$B6) -> - | I6: =IF($D6=0,"-",$E6/$D6) -> -
A7: C · Belleza | B7: =COUNTIFS(Leads!$F$7:$F$305,$A7) -> 0 | C7: =COUNTIFS(Leads!$F$7:$F$305,$A7,Leads!$H$7:$H$305,"Sí") -> 0 | D7: =SUM('Gasto diario'!$D$5:$D$95) -> 0 | E7: =SUMIFS(Leads!$I$7:$I$305,Leads!$F$7:$F$305,$A7,Leads!$H$7:$H$305,"Sí") -> 0 | F7: =IF($B7=0,"-",$D7/$B7) -> - | G7: =IF($C7=0,"-",$D7/$C7) -> - | H7: =IF($B7=0,"-",$C7/$B7) -> - | I7: =IF($D7=0,"-",$E7/$D7) -> -
A8: D · Amplio | B8: =COUNTIFS(Leads!$F$7:$F$305,$A8) -> 0 | C8: =COUNTIFS(Leads!$F$7:$F$305,$A8,Leads!$H$7:$H$305,"Sí") -> 0 | D8: =SUM('Gasto diario'!$E$5:$E$95) -> 0 | E8: =SUMIFS(Leads!$I$7:$I$305,Leads!$F$7:$F$305,$A8,Leads!$H$7:$H$305,"Sí") -> 0 | F8: =IF($B8=0,"-",$D8/$B8) -> - | G8: =IF($C8=0,"-",$D8/$C8) -> - | H8: =IF($B8=0,"-",$C8/$B8) -> - | I8: =IF($D8=0,"-",$E8/$D8) -> -
A9: TOTAL | B9: =SUM(B5:B8) -> 0 | C9: =SUM(C5:C8) -> 0 | D9: =SUM(D5:D8) -> 0 | E9: =SUM(E5:E8) -> 0 | F9: =IF($B9=0,"-",$D9/$B9) -> - | G9: =IF($C9=0,"-",$D9/$C9) -> - | H9: =IF($B9=0,"-",$C9/$B9) -> - | I9: =IF($D9=0,"-",$E9/$D9) -> -
A11: Resumen por creativo
A12: Creativo | B12: Leads | C12: Ventas | D12: Ingreso US$ | E12: Tasa de cierre
A13: 1 Demo | B13: =COUNTIFS(Leads!$G$7:$G$305,$A13) -> 0 | C13: =COUNTIFS(Leads!$G$7:$G$305,$A13,Leads!$H$7:$H$305,"Sí") -> 0 | D13: =SUMIFS(Leads!$I$7:$I$305,Leads!$G$7:$G$305,$A13,Leads!$H$7:$H$305,"Sí") -> 0 | E13: =IF($B13=0,"-",$C13/$B13) -> -
A14: 2 Problema | B14: =COUNTIFS(Leads!$G$7:$G$305,$A14) -> 0 | C14: =COUNTIFS(Leads!$G$7:$G$305,$A14,Leads!$H$7:$H$305,"Sí") -> 0 | D14: =SUMIFS(Leads!$I$7:$I$305,Leads!$G$7:$G$305,$A14,Leads!$H$7:$H$305,"Sí") -> 0 | E14: =IF($B14=0,"-",$C14/$B14) -> -
A15: 3 Objeción | B15: =COUNTIFS(Leads!$G$7:$G$305,$A15) -> 0 | C15: =COUNTIFS(Leads!$G$7:$G$305,$A15,Leads!$H$7:$H$305,"Sí") -> 0 | D15: =SUMIFS(Leads!$I$7:$I$305,Leads!$G$7:$G$305,$A15,Leads!$H$7:$H$305,"Sí") -> 0 | E15: =IF($B15=0,"-",$C15/$B15) -> -
A16: 4 Caso | B16: =COUNTIFS(Leads!$G$7:$G$305,$A16) -> 0 | C16: =COUNTIFS(Leads!$G$7:$G$305,$A16,Leads!$H$7:$H$305,"Sí") -> 0 | D16: =SUMIFS(Leads!$I$7:$I$305,Leads!$G$7:$G$305,$A16,Leads!$H$7:$H$305,"Sí") -> 0 | E16: =IF($B16=0,"-",$C16/$B16) -> -
A17: 5 Pena | B17: =COUNTIFS(Leads!$G$7:$G$305,$A17) -> 0 | C17: =COUNTIFS(Leads!$G$7:$G$305,$A17,Leads!$H$7:$H$305,"Sí") -> 0 | D17: =SUMIFS(Leads!$I$7:$I$305,Leads!$G$7:$G$305,$A17,Leads!$H$7:$H$305,"Sí") -> 0 | E17: =IF($B17=0,"-",$C17/$B17) -> -
A20: Cómo leerlo
A21: · Costo x venta es la métrica que decide, no el costo por lead. Un público barato que no cierra es caro.
A22: · Retorno = ingreso dividido entre gasto. Debajo de 1.00x estás perdiendo plata en ese público.
A23: · No saques conclusiones antes de 10 días ni con menos de 15 leads por público.
A24: · El ingreso no descuenta tu costo de producto ni el envío. Es venta bruta.

Sheet Leads
A1: Registro de leads · starTAP Panamá
A2: Llena SOLO las celdas con fondo amarillo. Las columnas grises se calculan solas.
A3: El código lo trae el cliente en su primer mensaje de WhatsApp. Sale del mensaje prellenado del anuncio.
A5: Fecha | B5: Nombre | C5: Negocio | D5: WhatsApp | E5: Código | F5: Público | G5: Creativo | H5: ¿Cerró? | I5: Monto US$ | J5: Producto | K5: Notas
A6: 2026-09-20 | B6: Onan Torres | C6: Barbería El Corte | D6: 60001234 | E6: A1 | F6: A · Admins | G6: 1 Demo | H6: Sí | I6: 30 | J6: Placa de mostrador | K6: Pidió factura | L6: <- fila de ejemplo, bórrala cuando empieces

Sheet Gasto diario
A1: Gasto de pauta por día y público
A2: Cópialo del Administrador de anuncios de Meta. Un renglón por día.
A4: Fecha | B4: A · Admins | C4: B · Gastronomía | D4: C · Belleza | E4: D · Amplio | F4: Total día
F5: =IF(COUNT(B5:E5)=0,"",SUM(B5:E5))
F6: =IF(COUNT(B6:E6)=0,"",SUM(B6:E6))
F7: =IF(COUNT(B7:E7)=0,"",SUM(B7:E7))
F8: =IF(COUNT(B8:E8)=0,"",SUM(B8:E8))
F9: =IF(COUNT(B9:E9)=0,"",SUM(B9:E9))
F10: =IF(COUNT(B10:E10)=0,"",SUM(B10:E10))
F11: =IF(COUNT(B11:E11)=0,"",SUM(B11:E11))
F12: =IF(COUNT(B12:E12)=0,"",SUM(B12:E12))
F13: =IF(COUNT(B13:E13)=0,"",SUM(B13:E13))
F14: =IF(COUNT(B14:E14)=0,"",SUM(B14:E14))
F15: =IF(COUNT(B15:E15)=0,"",SUM(B15:E15))
F16: =IF(COUNT(B16:E16)=0,"",SUM(B16:E16))
... F95: =IF(COUNT(B95:E95)=0,"",SUM(B95:E95))

Sheet Correos
A1: Correos recolectados · prospección en frío
A2: Llena solo las celdas amarillas. La columna "Válido" se calcula sola.
A3: ANTES DE ENVIAR: el dominio startap.com.pa no tiene SPF, DKIM ni DMARC. Sin eso los correos caen en spam.
A5: Fecha | B5: Negocio | C5: Rubro | D5: Zona | E5: Correo | F5: Válido | G5: Fuente | H5: Reseñas | I5: Estrellas | J5: Estado | K5: Fecha envío | L5: Respondió | M5: Notas | P5: Resumen
A6: 2026-09-20 | B6: Barbería El Corte | C6: Barberías | D6: Arraiján | E6: contacto@elcorte.com | G6: Ficha de Google | H6: 9 | I6: 4.8 | J6: pendiente | M6: Dueño: Luis | N6: <- ejemplo, bórralo | P6: Correos recolectados | Q6: =COUNTA($E$7:$E$306) -> 0
F7: =IF($E7="","",IF(AND(ISNUMBER(FIND("@",$E7)),ISNUMBER(FIND(".",$E7,FIND("@",$E7)))),"ok","revisar")) | P7: Con formato válido | Q7: =COUNTIF($F$7:$F$306,"ok") -> 0
F8: =IF($E8="","",IF(AND(ISNUMBER(FIND("@",$E8)),ISNUMBER(FIND(".",$E8,FIND("@",$E8)))),"ok","revisar")) | P8: Enviados | Q8: =COUNTIF($J$7:$J$306,"enviado")+COUNTIF($J$7:$J$306,"respondió")+COUNTIF($J$7:$J$306,"vendido") -> 0
F9: =IF($E9="","",IF(AND(ISNUMBER(FIND("@",$E9)),ISNUMBER(FIND(".",$E9,FIND("@",$E9)))),"ok","revisar")) | P9: Rebotaron | Q9: =COUNTIF($J$7:$J$306,"rebotó") -> 0
F10: =IF($E10="","",IF(AND(ISNUMBER(FIND("@",$E10)),ISNUMBER(FIND(".",$E10,FIND("@",$E10)))),"ok","revisar")) | P10: Respondieron | Q10: =COUNTIF($L$7:$L$306,"Sí") -> 0
F11: =IF($E11="","",IF(AND(ISNUMBER(FIND("@",$E11)),ISNUMBER(FIND(".",$E11,FIND("@",$E11)))),"ok","revisar")) | P11: Vendidos | Q11: =COUNTIF($J$7:$J$306,"vendido") -> 0
F12: =IF($E12="","",IF(AND(ISNUMBER(FIND("@",$E12)),ISNUMBER(FIND(".",$E12,FIND("@",$E12)))),"ok","revisar"))
F13: =IF($E13="","",IF(AND(ISNUMBER(FIND("@",$E13)),ISNUMBER(FIND(".",$E13,FIND("@",$E13)))),"ok","revisar")) | P13: Tasa de respuesta | Q13: =IF($Q$8=0,"-",$Q$10/$Q$8) -> -
F14: =IF($E14="","",IF(AND(ISNUMBER(FIND("@",$E14)),ISNUMBER(FIND(".",$E14,FIND("@",$E14)))),"ok","revisar"))
F15: =IF($E15="","",IF(AND(ISNUMBER(FIND("@",$E15)),ISNUMBER(FIND(".",$E15,FIND("@",$E15)))),"ok","revisar")) | P15: Si "Rebotaron" pasa de 3%, para y revisa
F16: =IF($E16="","",IF(AND(ISNUMBER(FIND("@",$E16)),ISNUMBER(FIND(".",$E16,FIND("@",$E16)))),"ok","revisar")) | P16: la autenticación del dominio.
F17: =IF($E17="","",IF(AND(ISNUMBER(FIND("@",$E17)),ISNUMBER(FIND(".",$E17,FIND("@",$E17)))),"ok","revisar"))
F18: =IF($E18="","",IF(AND(ISNUMBER(FIND("@",$E18)),ISNUMBER(FIND(".",$E18,FIND("@",$E18)))),"ok","revisar"))
F19: =IF($E19="","",IF(AND(ISNUMBER(FIND("@",$E19)),ISNUMBER(FIND(".",$E19,FIND("@",$E19)))),"ok","revisar"))
F20: =IF($E20="","",IF(AND(ISNUMBER(FIND("@",$E20)),ISNUMBER(FIND(".",$E20,FIND("@",$E20)))),"ok","revisar"))
F21: =IF($E21="","",IF(AND(ISNUMBER(FIND("@",$E21)),ISNUMBER(FIND(".",$E21,FIND("@",$E21)))),"ok","revisar"))
F22: =IF($E22="","",IF(AND(ISNUMBER(FIND("@",$E22)),ISNUMBER(FIND(".",$E22,FIND("@",$E22)))),"ok","revisar"))
F23: =IF($E23="","",IF(AND(ISNUMBER(FIND("@",$E23)),ISNUMBER(FIND(".",$E23,FIND("@",$E23)))),"ok","revisar"))
F24: =IF($E24="","",IF(AND(ISNUMBER(FIND("@",$E24)),ISNUMBER(FIND(".",$E24,FIND("@",$E24)))),"ok","revisar"))
F25: =IF($E25="","",IF(AND(ISNUMBER(FIND("@",$E25)),ISNUMBER(FIND(".",$E25,FIND("@",$E25)))),"ok","revisar"))
F26: =IF($E26="","",IF(AND(ISNUMBER(FIND("@",$E26)),ISNUMBER(FIND(".",$E26,FIND("@",$E26)))),"ok","revisar"))
F27: =IF($E27="","",IF(AND(ISNUMBER(FIND("@",$E27)),ISNUMBER(FIND(".",$E27,FIND("@",$E27)))),"ok","revisar"))
F28: =IF($E28="","",IF(AND(ISNUMBER(FIND("@",$E28)),ISNUMBER(FIND(".",$E28,FIND("@",$E28)))),"ok","revisar"))
... F306: =IF($E306="","",IF(AND(ISNUMBER(FIND("@",$E306)),ISNUMBER(FIND(".",$E306,FIND("@",$E306)))),"ok","revisar"))
